clox/__init__.py
clox/__main__.py
clox/functions.py
clox/jcalendar.py
clox/params.py
clox-1.5.dist-info/licenses/AUTHORS.md
clox-1.5.dist-info/licenses/LICENSE
clox-1.5.dist-info/METADATA
clox-1.5.dist-info/WHEEL
clox-1.5.dist-info/entry_points.txt
clox-1.5.dist-info/top_level.txt
clox-1.5.dist-info/RECORD
