Metadata-Version: 2.4
Name: clox
Version: 1.5
Summary: A Geeky Clock for Terminal Enthusiasts
Home-page: https://github.com/sepandhaghighi/clox
Download-URL: https://github.com/sepandhaghighi/clox/tarball/v1.5
Author: Sepand Haghighi
Author-email: me@sepand.tech
License: MIT
Project-URL: Source, https://github.com/sepandhaghighi/clox
Keywords: clock time timer timezone terminal cli geek clox
Classifier: Development Status :: 5 - Production/Stable
Classifier: Natural Language :: English
Classifier: License :: OSI Approved :: MIT License
Classifier: Operating System :: OS Independent
Classifier: Programming Language :: Python :: 3.7
Classifier: Programming Language :: Python :: 3.8
Classifier: Programming Language :: Python :: 3.9
Classifier: Programming Language :: Python :: 3.10
Classifier: Programming Language :: Python :: 3.11
Classifier: Programming Language :: Python :: 3.12
Classifier: Programming Language :: Python :: 3.13
Classifier: Programming Language :: Python :: 3.14
Classifier: Intended Audience :: Developers
Classifier: Intended Audience :: Education
Classifier: Intended Audience :: End Users/Desktop
Classifier: Intended Audience :: Other Audience
Classifier: Topic :: Games/Entertainment
Classifier: Topic :: Utilities
Requires-Python: >=3.7
License-File: LICENSE
License-File: AUTHORS.md
Requires-Dist: art>=5.3
Requires-Dist: jdatetime>=3.8.2
Requires-Dist: pytz>=2019.2
Requires-Dist: colorama>=0.4.5
Dynamic: author
Dynamic: author-email
Dynamic: classifier
Dynamic: description
Dynamic: description-content-type
Dynamic: download-url
Dynamic: home-page
Dynamic: keywords
Dynamic: license
Dynamic: license-file
Dynamic: project-url
Dynamic: requires-dist
Dynamic: requires-python
Dynamic: summary
